{"largeur":11,"hauteur":11,"gains":[[1,1,1,10,-10,-20,-40,-80,-100,42],[1,1,1,10,-10,-20,-40,-80,-100,-100],[1,1,1,10,-10,-20,-40,-80,-80,-80],[10,10,10,10,10,10,10,-40,-40,-40],[-10,-10,-10,10,42,42,10,-20,-20,-20],[-20,-20,-20,10,42,42,10,-10,-10,-10],[-40,-40,-40,10,10,10,10,10,10,10],[-80,-80,-80,-40,-20,-10,10,1,1,1],[-100,-100,-80,-40,-20,-10,10,1,1,1],[42,-100,-80,-40,-20,-10,10,1,1,1]],"carte":["44331111443","1X33XXXX432","1223XXXX322","12244441XX1","3XX42212XX1","3XX42X42XX1","3XX43442XX1","3XX32222333","443XXXX4433","412XXXX44X2","12233331112"],"aigles":[{"pos":{"x":8,"y":1},"effet":"GEL","puissance":40,"tour_eclosion":1},{"pos":{"x":1,"y":8},"effet":"GEL","puissance":40,"tour_eclosion":1},{"pos":{"x":6,"y":3},"effet":"METEORE","puissance":40,"tour_eclosion":1},{"pos":{"x":3,"y":6},"effet":"METEORE","puissance":40,"tour_eclosion":1},{"pos":{"x":9,"y":3},"effet":"VIE","puissance":40,"tour_eclosion":1},{"pos":{"x":3,"y":9},"effet":"VIE","puissance":40,"tour_eclosion":1},{"pos":{"x":8,"y":4},"effet":"FEU","puissance":-5,"tour_eclosion":1},{"pos":{"x":8,"y":5},"effet":"FEU","puissance":5,"tour_eclosion":1},{"pos":{"x":5,"y":8},"effet":"FEU","puissance":5,"tour_eclosion":1},{"pos":{"x":4,"y":8},"effet":"FEU","puissance":-5,"tour_eclosion":1},{"pos":{"x":8,"y":1},"effet":"GEL","puissance":40,"tour_eclosion":1},{"pos":{"x":1,"y":8},"effet":"GEL","puissance":40,"tour_eclosion":1},{"pos":{"x":6,"y":3},"effet":"METEORE","puissance":40,"tour_eclosion":1},{"pos":{"x":3,"y":6},"effet":"METEORE","puissance":40,"tour_eclosion":1},{"pos":{"x":6,"y":0},"effet":"VIE","puissance":40,"tour_eclosion":1},{"pos":{"x":0,"y":6},"effet":"VIE","puissance":40,"tour_eclosion":1},{"pos":{"x":5,"y":1},"effet":"FEU","puissance":-5,"tour_eclosion":1},{"pos":{"x":4,"y":1},"effet":"FEU","puissance":5,"tour_eclosion":1},{"pos":{"x":1,"y":4},"effet":"FEU","puissance":5,"tour_eclosion":1},{"pos":{"x":1,"y":5},"effet":"FEU","puissance":-5,"tour_eclosion":1}],"joueur1":{"x":1,"y":1},"joueur2":{"x":9,"y":9}}
